dbflows/__init__.py
dbflows/caggs.py
dbflows/cli.py
dbflows/compare.py
dbflows/conn.py
dbflows/create.py
dbflows/duck.py
dbflows/export.py
dbflows/files.py
dbflows/functions.py
dbflows/load.py
dbflows/meta.py
dbflows/read.py
dbflows/schedule.py
dbflows/tables.py
dbflows/transfer.py
dbflows/utils.py
dbflows/views.py
dbflows/components/__init__.py
dbflows/components/base.py
dbflows/components/caggs.py
dbflows/components/functions.py
dbflows/components/schedule.py
dbflows/components/tables.py
dbflows/components/views.py
dbflows-0.2.6.dist-info/METADATA
dbflows-0.2.6.dist-info/WHEEL
dbflows-0.2.6.dist-info/entry_points.txt
dbflows-0.2.6.dist-info/top_level.txt
dbflows-0.2.6.dist-info/RECORD
