Metadata-Version: 2.2
Name: dbflows
Version: 0.2.6
Summary: Database incremental exports, transfers, imports, ETL, creation / management
Author-email: Dan Kelleher <kelleherjdan@gmail.com>
License: MIT
Classifier: Programming Language :: Python
Classifier: Programming Language :: Python :: 3
Classifier: Topic :: Software Development
Classifier: Topic :: Software Development :: Libraries
Classifier: Topic :: Software Development :: Libraries :: Python Modules
Requires-Dist: async_lru
Requires-Dist: fileflows
Requires-Dist: sqlalchemy>=2.0.0
Requires-Dist: quicklogs>=2.0.0
Requires-Dist: dynamic-imports
Requires-Dist: asyncclick
Requires-Dist: tqdm
Requires-Dist: pydantic>=2.0.0
Requires-Dist: cytoolz
Requires-Dist: pandas>=2.0.0
Requires-Dist: asyncpg
Requires-Dist: ujson
Requires-Dist: duckdb>=1.0.0
Requires-Dist: xxhash
Provides-Extra: dev
Requires-Dist: psycopg[binary]; extra == "dev"
Requires-Dist: black; extra == "dev"
Requires-Dist: pytest; extra == "dev"
Requires-Dist: pytest-asyncio; extra == "dev"
Requires-Dist: faker; extra == "dev"
Requires-Dist: python-dotenv; extra == "dev"
Requires-Dist: jupyter; extra == "dev"
